pyimaging/__init__.py
pyimaging/font/青鸟华光简琥珀.ttf
pyimaging/main.py
pyimaging/marker.py
pyimaging-0.2.1.dist-info/entry_points.txt
pyimaging-0.2.1.dist-info/LICENSE
pyimaging-0.2.1.dist-info/METADATA
pyimaging-0.2.1.dist-info/WHEEL
pyimaging-0.2.1.dist-info/RECORD
