Metadata-Version: 2.1
Name: pyimaging
Version: 0.2.1
Summary: 轻量级 Python 图像处理
Home-page: https://github.com/yiyungent/imaging
License: Apache-2.0
Author: yiyun
Author-email: yiyungent@gmail.com
Requires-Python: >=3.8,<4.0
Classifier: License :: OSI Approved :: Apache Software License
Classifier: Programming Language :: Python :: 3
Classifier: Programming Language :: Python :: 3.8
Classifier: Programming Language :: Python :: 3.9
Classifier: Programming Language :: Python :: 3.10
Classifier: Programming Language :: Python :: 3.11
Classifier: Programming Language :: Python :: 3.12
Requires-Dist: blind-watermark (>=0.4.2,<0.5.0)
Requires-Dist: pillow (>=9.4.0,<10.0.0)
Requires-Dist: typer[all] (>=0.15.4,<0.16.0)
Project-URL: Repository, https://github.com/yiyungent/imaging
